Cyther-0.7.0.data/data/cyther/CHANGELOG.txt
Cyther-0.7.0.data/data/cyther/LICENSE.txt
Cyther-0.7.0.data/data/cyther/README.rst
Cyther-0.7.0.data/data/cyther/TODO.txt
Cyther-0.7.0.data/scripts/cytherize.py
Cyther-0.7.0.dist-info/DESCRIPTION.rst
Cyther-0.7.0.dist-info/METADATA
Cyther-0.7.0.dist-info/RECORD
Cyther-0.7.0.dist-info/WHEEL
Cyther-0.7.0.dist-info/metadata.json
Cyther-0.7.0.dist-info/top_level.txt
cyther/__init__.py
cyther/cyther.py
cyther/script.py
