Metadata-Version: 2.0
Name: Cyther
Version: 0.7.0
Summary: The Cross-Platform Cython/Python Compiler
Home-page: https://github.com/nickpandolfi/Cyther
Author: Nicholas C. Pandolfi
Author-email: npandolfi@wpi.edu
License: MIT
Keywords: Cyther,Cython,Python,MinGW32,vcvarsall.bat,vcvarsall not found,setup.py,gcc,Python 3,user-friendly,command-line,script,auto-compiler
Platform: Windows
Platform: MacOS
Platform: POSIX
Platform: Unix
Classifier: Development Status :: 3 - Alpha
Classifier: Environment :: Console
Classifier: Topic :: Software Development :: Compilers
Classifier: Topic :: Software Development :: Build Tools
Classifier: Topic :: Desktop Environment :: File Managers
Classifier: Intended Audience :: Developers
Classifier: Intended Audience :: Science/Research
Classifier: Operating System :: OS Independent
Classifier: Programming Language :: Python
Classifier: Programming Language :: Python :: 3.5
Classifier: Programming Language :: Python :: 3.4
Classifier: Programming Language :: Python :: 3.3
Classifier: Programming Language :: Cython
Classifier: License :: OSI Approved :: MIT License
